[{"title":"프로 바둑기사 장두진 8단 별세","subtitle":"\n(서울=연합뉴스) 최인영 기자 = 프로 바둑기사 장두진 8단이 27일 지병으로 별세했다. 향년 67세.\n고인은 1972년 ...","src":"http://img5.yna.co.kr/etc/inner/KR/2020/08/27/AKR20200827154600007_01_i_P2.jpg","a":"https://www.yna.co.kr/view/AKR20200827154600007?section=news"},{"title":"헤리티지재단 \"북한경제 '퍼펙트스톰'…미국 인도적 지원 하라\"","subtitle":"제재·코로나·수해 '삼중고'…\"북한 거부에도 계속 제안 필요\"\n비핵화 협상 진전·남북관계 개선 위한 제재완화엔 반대 견해\n(서...","src":"http://img4.yna.co.kr/photo/yna/YH/2020/08/07/PYH2020080714390004200_P2.jpg","a":"https://www.yna.co.kr/view/AKR20200827151300009?section=news"},{"title":"코로나19 확산 속 청주 시민단체 길거리 집회 강행 '눈총'","subtitle":"주최 측 \"29일 차별금지법 저지대회 30∼50명으로 축소 진행\"\n청주시 긴급 대책회의…\"이 시국에 꼭 해야 하나\" 시민 눈총\n...","src":"http://img3.yna.co.kr/etc/inner/KR/2020/08/27/AKR20200827145100064_01_i_P2.jpg","a":"https://www.yna.co.kr/view/AKR20200827145100064?section=news"},{"title":"다저스-샌프란시스코 보이콧 이끈 무키 베츠의 리더십","subtitle":"베츠, 인종차별 항의 뜻으로 결장 선언…다른 선수들 동참\n(서울=연합뉴스) 최인영 기자 = 27일(한국시간) 미국 캘리포니아주 샌...","src":"http://img8.yna.co.kr/photo/ap/2020/08/18/PAP20200818186201055_P2.jpg","a":"https://www.yna.co.kr/view/AKR20200827152600007?section=news"},{"title":"코로나19 확산 속 인도 의·공대 입시 시험 강행 논란","subtitle":"당국 \"예정대로 내달 시험\"…학생·일부 주 총리 \"연기 필요\"\n(뉴델리=연합뉴스) 김영현 특파원 = 인도 교육 당국이 신종...","src":"http://img0.yna.co.kr/etc/inner/KR/2020/08/27/AKR20200827154400077_01_i_P2.jpg","a":"https://www.yna.co.kr/view/AKR20200827154400077?section=news"},{"title":"태풍 '바비' 중국 선양 인근에서 소멸…폭염경보 확대","subtitle":"\n(서울=연합뉴스) 고은지 기자 = 제8호 태풍 '바비'가 27일 오후 3시 소멸했다.\n기상청은 바비가 중국 선양 동쪽 18...","src":"http://img5.yna.co.kr/photo/yna/YH/2020/08/27/PYH2020082713900006500_P2.jpg","a":"https://www.yna.co.kr/view/AKR20200827153700530?section=news"},{"title":"용인시, 올해분 교통유발부담금 30% 감면…소상공인 지원","subtitle":"\n(용인=연합뉴스) 김인유 기자 = 경기 용인시는 올해분 교통유발부담금을 30% 감면해 부과한다고 27일 밝혔다.\n...","src":"http://img5.yna.co.kr/photo/cms/2020/07/31/32/PCM20200731000032061_P2.jpg","a":"https://www.yna.co.kr/view/AKR20200827153600061?section=news"},{"title":"대입 수시전형도 비대면…극동대 \"영상녹화 방식 면접\"","subtitle":"\n(청주=연합뉴스) 변우열 기자 = 충북 음성군 소재 극동대는 2021학년도 수시모집 전형에서 비대면 면접을 시행한다고 27일 밝혔다...","src":"http://img7.yna.co.kr/etc/inner/KR/2020/08/27/AKR20200827150500064_01_i_P2.jpg","a":"https://www.yna.co.kr/view/AKR20200827150500064?section=news"},{"title":"[2보] 금융위, 상장종목 전체 공매도 금지 6개월 추가 연장","subtitle":"\n(서울=연합뉴스) 김남권 기자 = 금융위원회는 27일 공매도 금지를 6개월 추가 연장하기로 했다고 밝혔다.\n이에 따라 다...","src":"http://img8.yna.co.kr/photo/cms/2018/04/09/01/C0A8CA3D00000162A855BEB60023FF2D_P2.jpeg","a":"https://www.yna.co.kr/view/AKR20200827153400002?section=news"},{"title":"지난주 청와대 인근에서 정부 비판 기자회견 한 목사 확진","subtitle":"다른 참석자들과 경찰은 감염 안 된 듯\n(서울=연합뉴스) 정성조 기자 = 정부의 대면 예배 금지 조치 등을 두고 '방역 ...","src":"http://img2.yna.co.kr/photo/yna/YH/2020/08/20/PYH2020082011980001300_P2.jpg","a":"https://www.yna.co.kr/view/AKR20200827151400004?section=news"},{"title":"[문화소식] 부산민속문화의 해 주제별 조사 보고서","subtitle":"'수어로 묻고 답하기' 서비스·'신식부인치가법의 번역과 어휘' 발간\n(서울=연합뉴스) 강종훈 기자 = ▲ 국립민속박물관과 부산광역시...","src":"http://img9.yna.co.kr/etc/inner/KR/2020/08/27/AKR20200827151500005_01_i_P2.jpg","a":"https://www.yna.co.kr/view/AKR20200827151500005?section=news"},{"title":"에이프로 \"종속회사 에이프로세미콘 주식 60억원에 추가취득\"","subtitle":"\n(서울=연합뉴스) 코스닥 상장사 에이프로[262260]는 GaN 전력반도체 종속회사 에이프로세미콘의 주식 119만주를 약 60억원...","src":"http://img4.yna.co.kr/photo/cms/2020/07/11/58/PCM20200711000058002_P2.jpg","a":"https://www.yna.co.kr/view/AKR20200827153500002?section=news"},{"title":"과기부 \"코로나19 감염모델 햄스터·마우스 9월 기업에 제공\"","subtitle":"최기영 장관 \"치료제·백신 개발 위해 국가적 연구 역량·자원 총력 지원\"\n(서울=연합뉴스) 이주영 기자 = 과학기술정보통신부는 국내...","src":"http://img9.yna.co.kr/etc/inner/KR/2020/08/27/AKR20200827127300017_01_i_P2.jpg","a":"https://www.yna.co.kr/view/AKR20200827127300017?section=news"},{"title":"주한외교단 등 대상 '한국판 뉴딜' 정책공유 웹세미나 개최","subtitle":"\n한-콜롬비아 양자면담 개최\n(세종=연합뉴스) 김연정 기자 = 정부는 27일 주한외교단, 외신·국제기구 등 130여명이 참석한 가운...","src":"http://img3.yna.co.kr/photo/cms/2020/03/05/08/PCM20200305000108990_P2.jpg","a":"https://www.yna.co.kr/view/AKR20200827153200002?section=news"},{"title":"경남도, 공간정보 기반한 '스마트 행정' 편다","subtitle":"\n(창원=연합뉴스) 황봉규 기자 = 경남도가 공간정보에 기반한 '스마트 행정'을 편다.\n경남도는 27일 도청에서 '4차 산...","src":"http://img2.yna.co.kr/etc/inner/KR/2020/08/27/AKR20200827151200052_01_i_P2.jpg","a":"https://www.yna.co.kr/view/AKR20200827151200052?section=news"},{"title":"코로나 재확산에 '승리호' 등 가을 대작 또 개봉 연기(종합)","subtitle":"디즈니 '뮬란'·'뉴 뮤턴트'도 일주일씩 미뤄\n(서울=연합뉴스) 한미희 기자 = 신종 코로나바이러스 감염증(코로나19)이 재확산하면...","src":"http://img5.yna.co.kr/etc/inner/KR/2020/08/27/AKR20200827040151005_02_i_P2.jpg","a":"https://www.yna.co.kr/view/AKR20200827040151005?section=news"},{"title":"파주서 1명 추가 확진…사랑제일교회 교인 접촉","subtitle":"\n(파주=연합뉴스) 노승혁 기자 = 경기 파주시는 신종 코로나바이러스 감염증(코로나19) 확진자 1명(파주 92번)이 추가 발생했다고...","src":"http://img9.yna.co.kr/photo/cms/2020/07/07/21/PCM20200707000121990_P2.jpg","a":"https://www.yna.co.kr/view/AKR20200827152700060?section=news"},{"title":"중국인 유학생 부부, 가천대서 차례로 박사 학위 취득","subtitle":"\n서전화·사문도씨 부부 \"한중교류 확대에 적극적으로 참여할 것\"\n(성남=연합뉴스) 최찬흥 기자 = 중국인 유학생 부부가 가천대학교 ...","src":"http://img1.yna.co.kr/etc/inner/KR/2020/08/27/AKR20200827151100061_01_i_P2.jpg","a":"https://www.yna.co.kr/view/AKR20200827151100061?section=news"},{"title":"\"성매매 업주 이익 취득한 만큼만 추징해야\" 법원 판결","subtitle":"\n(울산=연합뉴스) 허광무 기자 = 성매매 업소 운영으로 취득한 이익을 추징하더라도, 전체 이익이 아니라 피고인이 실제 취한 만큼만...","src":"http://img4.yna.co.kr/photo/cms/2019/05/13/95/PCM20190513000295990_P2.jpg","a":"https://www.yna.co.kr/view/AKR20200827152100057?section=news"},{"title":"KAMC \"코로나19 속 의대생 국가고시 최소 2주 이상 연기해야\"","subtitle":"\"정부가 의대생들 교육현장에 되돌려 놓아야…정책 졸속추진 반대\"\n(서울=연합뉴스) 계승현 기자 = 한국의과대학의학전문대학원협회(KA...","src":"http://img6.yna.co.kr/photo/yna/YH/2020/08/27/PYH2020082715030001300_P2.jpg","a":"https://www.yna.co.kr/view/AKR20200827146900017?section=news"},{"title":"주행 모드에서 하차하다…운전자 차량과 벽에 끼여","subtitle":"\n(부산=연합뉴스) 손형주 기자 = 27일 오전 7시 20분께 부산 동구 수정동 한 건물 지하주차장에서 40대 승용차 운전자 A씨...","src":"http://img0.yna.co.kr/etc/inner/KR/2020/08/27/AKR20200827151900051_01_i_P2.jpg","a":"https://www.yna.co.kr/view/AKR20200827151900051?section=news"},{"title":"[1보] 금융위, 공매도 금지 6개월 연장","subtitle":"\n","src":"http://img9.yna.co.kr/photo/yna/YH/2020/08/27/PYH2020082712650001300_P2.jpg","a":"https://www.yna.co.kr/view/AKR20200827152200002?section=news"},{"title":"국회, 모레까지 폐쇄…정기국회는 예정대로","subtitle":"\n(서울=연합뉴스) 이유미 기자 = 국회가 신종 코로나바이러스 감염증(코로나19) 확진자 발생에 따른 방역 작업을 위해 오는 2...","src":"http://img9.yna.co.kr/photo/yna/YH/2020/08/27/PYH2020082715260001300_P2.jpg","a":"https://www.yna.co.kr/view/AKR20200827150900001?section=news"}]